sentinelloader/__init__.py
sentinelloader/sentinel2loader.py
sentinelloader/utils.py
sentinelloader-1.1.1.dist-info/LICENSE
sentinelloader-1.1.1.dist-info/METADATA
sentinelloader-1.1.1.dist-info/WHEEL
sentinelloader-1.1.1.dist-info/top_level.txt
sentinelloader-1.1.1.dist-info/RECORD
