Metadata-Version: 2.1
Name: sentinelloader
Version: 1.1.1
Summary: Sentinel-2 satellite tiles images downloader from Copernicus
Home-page: https://github.com/flaviostutz/sentinelloader.git
Author: Flávio Stutz
Author-email: Flavio Stutz <flaviostutz@gmail.com>
License: MIT License        
Project-URL: Homepage, https://github.com/flaviostutz/sentinelloader
Project-URL: Bug Tracker, https://github.com/flaviostutz/sentinelloader/issues
Classifier: Programming Language :: Python :: 3
Classifier: License :: OSI Approved :: MIT License
Classifier: Operating System :: OS Independent
Requires-Python: >=3.7
License-File: LICENSE
Requires-Dist: uuid (>=1.3.0)
Requires-Dist: gdal (>=2.2.2)
Requires-Dist: requests (>=2.21.0)
Requires-Dist: pandas (>=0.24.1)
Requires-Dist: geopandas (>=0.4.1)
Requires-Dist: shapely (>=1.6.4)
Requires-Dist: sentinelsat (>=0.12.2)
